{"mean":{"confidence_interval":{"confidence_level":0.95,"lower_bound":786060.5692423071,"upper_bound":787018.9082115376},"point_estimate":786532.4143076922,"standard_error":242.882956412321},"median":{"confidence_interval":{"confidence_level":0.95,"lower_bound":785522.2307692308,"upper_bound":785913.3846153846},"point_estimate":785726.9615384615,"standard_error":102.99035292316182},"median_abs_dev":{"confidence_interval":{"confidence_level":0.95,"lower_bound":1814.9304600861028,"upper_bound":2518.4811706727296},"point_estimate":2124.6798084333454,"standard_error":178.0962137021706},"slope":null,"std_dev":{"confidence_interval":{"confidence_level":0.95,"lower_bound":4967.915811447999,"upper_bound":5880.822267727977},"point_estimate":5440.4042127849425,"standard_error":232.94684470245895}}