{"mean":{"confidence_interval":{"confidence_level":0.95,"lower_bound":992717.0769166932,"upper_bound":995991.6703294371},"point_estimate":994283.6397254567,"standard_error":833.6533368064484},"median":{"confidence_interval":{"confidence_level":0.95,"lower_bound":991018.1996779388,"upper_bound":993743.5714285715},"point_estimate":992075.5142307692,"standard_error":671.2646467526498},"median_abs_dev":{"confidence_interval":{"confidence_level":0.95,"lower_bound":3622.7772862757743,"upper_bound":6851.333876546242},"point_estimate":4882.058927672191,"standard_error":848.1748320230839},"slope":{"confidence_interval":{"confidence_level":0.95,"lower_bound":990988.7040796835,"upper_bound":995108.0831686165},"point_estimate":992751.0959272942,"standard_error":1064.4795302318382},"std_dev":{"confidence_interval":{"confidence_level":0.95,"lower_bound":6359.136159399327,"upper_bound":10219.947416947116},"point_estimate":8396.846855598636,"standard_error":988.0134771057428}}