{"mean":{"confidence_interval":{"confidence_level":0.95,"lower_bound":37945.03934349096,"upper_bound":38102.24889103969},"point_estimate":38018.76290903234,"standard_error":40.09605095144006},"median":{"confidence_interval":{"confidence_level":0.95,"lower_bound":37938.14926739927,"upper_bound":38048.35008741259},"point_estimate":38017.78421578422,"standard_error":28.924150751198834},"median_abs_dev":{"confidence_interval":{"confidence_level":0.95,"lower_bound":132.1314922157889,"upper_bound":211.8402090861545},"point_estimate":176.0399134278369,"standard_error":22.00691084335931},"slope":{"confidence_interval":{"confidence_level":0.95,"lower_bound":37909.29097597834,"upper_bound":38089.25336569888},"point_estimate":37984.81986518284,"standard_error":46.60098614775359},"std_dev":{"confidence_interval":{"confidence_level":0.95,"lower_bound":212.99010084172752,"upper_bound":553.1645870615256},"point_estimate":403.2160321364273,"standard_error":85.08586401761842}}