{"mean":{"confidence_interval":{"confidence_level":0.95,"lower_bound":53647.940081493376,"upper_bound":53788.81898020343},"point_estimate":53712.15833775197,"standard_error":36.06884796339211},"median":{"confidence_interval":{"confidence_level":0.95,"lower_bound":53611.98026315789,"upper_bound":53636.278195488725},"point_estimate":53628.122028862475,"standard_error":6.617019678454505},"median_abs_dev":{"confidence_interval":{"confidence_level":0.95,"lower_bound":45.4231648901786,"upper_bound":77.27567762687119},"point_estimate":62.07215752727534,"standard_error":8.000591391870962},"slope":{"confidence_interval":{"confidence_level":0.95,"lower_bound":53614.56699447896,"upper_bound":53829.125687234075},"point_estimate":53703.189342708036,"standard_error":55.891870784678126},"std_dev":{"confidence_interval":{"confidence_level":0.95,"lower_bound":196.67515491750683,"upper_bound":490.1955524214724},"point_estimate":362.4168246738824,"standard_error":75.39318359773866}}