{"mean":{"confidence_interval":{"confidence_level":0.95,"lower_bound":41436.15877781077,"upper_bound":41482.29646066109},"point_estimate":41455.77105037616,"standard_error":11.937085594777859},"median":{"confidence_interval":{"confidence_level":0.95,"lower_bound":41431.17401640535,"upper_bound":41450.49234693877},"point_estimate":41439.38803763441,"standard_error":4.2564813547599964},"median_abs_dev":{"confidence_interval":{"confidence_level":0.95,"lower_bound":31.920396588341315,"upper_bound":56.4398100758846},"point_estimate":43.5896076975363,"standard_error":6.109918154715178},"slope":{"confidence_interval":{"confidence_level":0.95,"lower_bound":41441.65510749536,"upper_bound":41463.97755488238},"point_estimate":41452.09556327274,"standard_error":5.664565826236961},"std_dev":{"confidence_interval":{"confidence_level":0.95,"lower_bound":48.67361413841009,"upper_bound":187.93340769348907},"point_estimate":120.35826799792683,"standard_error":41.381260588719634}}