{"mean":{"confidence_interval":{"confidence_level":0.95,"lower_bound":35896.02350555291,"upper_bound":35923.87541667971},"point_estimate":35909.601774838135,"standard_error":7.064877025668418},"median":{"confidence_interval":{"confidence_level":0.95,"lower_bound":35903.40714285714,"upper_bound":35917.92887507229},"point_estimate":35909.25174308854,"standard_error":3.7498773857076095},"median_abs_dev":{"confidence_interval":{"confidence_level":0.95,"lower_bound":27.99567678238799,"upper_bound":47.82761961825729},"point_estimate":39.594686885523636,"standard_error":5.147405035537203},"slope":{"confidence_interval":{"confidence_level":0.95,"lower_bound":35910.340417005755,"upper_bound":35921.78146486365},"point_estimate":35916.32595220503,"standard_error":2.9143312279610165},"std_dev":{"confidence_interval":{"confidence_level":0.95,"lower_bound":48.15753079755384,"upper_bound":91.48430323556887},"point_estimate":71.34241085405056,"standard_error":11.102929577295004}}