{"mean":{"confidence_interval":{"confidence_level":0.95,"lower_bound":181230.09249654153,"upper_bound":181938.9527425522},"point_estimate":181618.16531108026,"standard_error":181.47174323547483},"median":{"confidence_interval":{"confidence_level":0.95,"lower_bound":181968.75,"upper_bound":182081.2507936508},"point_estimate":182048.79730902778,"standard_error":32.63949413746662},"median_abs_dev":{"confidence_interval":{"confidence_level":0.95,"lower_bound":136.10660871999758,"upper_bound":451.80420787952824},"point_estimate":251.14119405810894,"standard_error":80.87720037748264},"slope":{"confidence_interval":{"confidence_level":0.95,"lower_bound":181362.63804871662,"upper_bound":181640.6366476495},"point_estimate":181494.75782720064,"standard_error":70.86723744911309},"std_dev":{"confidence_interval":{"confidence_level":0.95,"lower_bound":788.7143286816698,"upper_bound":2635.7763777355235},"point_estimate":1828.614399360945,"standard_error":473.91208321003774}}