{"mean":{"confidence_interval":{"confidence_level":0.95,"lower_bound":57960.09001050288,"upper_bound":78895.67983261266},"point_estimate":67873.97221397393,"standard_error":5420.038079786116},"median":{"confidence_interval":{"confidence_level":0.95,"lower_bound":48001.28913043478,"upper_bound":48348.99882491187},"point_estimate":48341.409968009306,"standard_error":94.38044165425704},"median_abs_dev":{"confidence_interval":{"confidence_level":0.95,"lower_bound":30.991811608112315,"upper_bound":1420.6297893944736},"point_estimate":919.3769841009453,"standard_error":404.38085365283376},"slope":{"confidence_interval":{"confidence_level":0.95,"lower_bound":55585.557960737126,"upper_bound":73363.0643213249},"point_estimate":63475.48336595113,"standard_error":4551.898657493864},"std_dev":{"confidence_interval":{"confidence_level":0.95,"lower_bound":39224.991649173346,"upper_bound":65501.94743775033},"point_estimate":54482.83904149607,"standard_error":6632.941056487423}}