{"mean":{"confidence_interval":{"confidence_level":0.95,"lower_bound":8591.262982059241,"upper_bound":8977.933232919439},"point_estimate":8759.01325476254,"standard_error":99.37176167401572},"median":{"confidence_interval":{"confidence_level":0.95,"lower_bound":8440.69797979798,"upper_bound":8540.041287878788},"point_estimate":8503.844597752308,"standard_error":27.533987070462622},"median_abs_dev":{"confidence_interval":{"confidence_level":0.95,"lower_bound":237.01711888792792,"upper_bound":383.9874484173975},"point_estimate":326.626468861569,"standard_error":38.924683654032016},"slope":{"confidence_interval":{"confidence_level":0.95,"lower_bound":8591.81101342314,"upper_bound":9023.886529465392},"point_estimate":8790.134702553838,"standard_error":110.96488722104445},"std_dev":{"confidence_interval":{"confidence_level":0.95,"lower_bound":474.5122686461806,"upper_bound":1510.720569926811},"point_estimate":998.2862866727046,"standard_error":303.342324996109}}